feapder_pipelines/VERSION
feapder_pipelines/__init__.py
feapder_pipelines/requirements.txt
feapder_pipelines/db/__init__.py
feapder_pipelines/db/pgsqldb.py
feapder_pipelines/pipelines/__init__.py
feapder_pipelines/pipelines/pgsql_pipeline.py
feapder_pipelines/utils/__init__.py
feapder_pipelines/utils/pgsql_tool.py
feapder_pipelines-1.0.3.dist-info/LICENSE
feapder_pipelines-1.0.3.dist-info/METADATA
feapder_pipelines-1.0.3.dist-info/WHEEL
feapder_pipelines-1.0.3.dist-info/top_level.txt
feapder_pipelines-1.0.3.dist-info/RECORD
