Metadata-Version: 2.1
Name: feapder-pipelines
Version: 1.0.3
Summary: feapder pipelines extension
Home-page: https://github.com/Boris-code/feapder_pipelines.git
Author: Boris
Author-email: feapder@qq.com
License: MIT
Platform: UNKNOWN
Classifier: Programming Language :: Python :: 3
Requires-Python: >=3.6
License-File: LICENSE
Requires-Dist: feapder
Provides-Extra: pgsql
Requires-Dist: psycopg2-binary (>=2.9.2) ; extra == 'pgsql'
